fc_pruning
